solidipes_solid_mech_plugin/__init__.py
solidipes_solid_mech_plugin/config.py
solidipes_solid_mech_plugin/loaders/__init__.py
solidipes_solid_mech_plugin/loaders/abaqus.py
solidipes_solid_mech_plugin/loaders/abaqus_python_code.py
solidipes_solid_mech_plugin/loaders/geo_msh.py
solidipes_solid_mech_plugin/loaders/geof_mesh.py
solidipes_solid_mech_plugin/loaders/meshio.py
solidipes_solid_mech_plugin/loaders/parse_inp.py
solidipes_solid_mech_plugin/loaders/pyvista_mesh.py
solidipes_solid_mech_plugin/loaders/xdmf.py
solidipes_solid_mech_plugin/viewers/__init__.py
solidipes_solid_mech_plugin/viewers/pyvista_plotter.py
solidipes_solid_mech_plugin/viewers/xdmf.py
solidipes_solid_mech_plugin-0.0.10.dist-info/licenses/LICENSE
solidipes_solid_mech_plugin-0.0.10.dist-info/METADATA
solidipes_solid_mech_plugin-0.0.10.dist-info/WHEEL
solidipes_solid_mech_plugin-0.0.10.dist-info/entry_points.txt
solidipes_solid_mech_plugin-0.0.10.dist-info/top_level.txt
solidipes_solid_mech_plugin-0.0.10.dist-info/RECORD
